{
  "insights": {
    "closest_division_races": [],
    "wild_card_battles": {
      "al_contenders": [],
      "nl_contenders": []
    },
    "world_series_favorites": [
      {
        "team": "UNK",
        "odds": 5.7
      }
    ],
    "elimination_watch": [],
    "last_updated": "2025-08-15 13:41:10"
  },
  "playoff_scenarios": {
    "al_division_winners": {},
    "nl_division_winners": {},
    "al_wild_card": {},
    "nl_wild_card": {},
    "world_series_odds": {
      "UNK": 5.7
    }
  },
  "team_strength": {
    "UNK": {
      "wins": 32,
      "losses": 89,
      "win_pct": 0.264,
      "projected_wins": 42.8,
      "strength_score": 0.044,
      "games_remaining": 41,
      "division": "NL Division"
    }
  }
}